abundance/Abundance.py
abundance/AbundanceApplication.py
abundance/banner/AbundanceApplicationBannerPrinter.py
abundance/banner/AbundanceBanner.py
abundance/banner/BannerMode.py
abundance/beans/factory/annotation/Value.py
abundance/bridge/bridge.py
abundance/bridge/route.py
abundance/context/Properties/ConfigurationProperties.py
abundance/core/env/ApplicationEnvironment.py
abundance/core/env/Environment.py
abundance/core/instance/component.py
abundance/core/instance/component_scan.py
abundance/core/instance/instance_container.py
abundance/core/properties/ConfigurationProperties.py
abundance/core/properties/Value.py
abundance/loader/PropertyLoader.py
abundance/loader/Resource.py
abundance/loader/ResourceLoader.py
abundance/log/LoggingSetup.py
abundance/pyqt/router.py
abundance/pyqt/store.py
abundance/util/data_utils.py
abundance/util/path_utils.py
abundance/util/StopWatch.py
abundance-0.0.1b0.dist-info/LICENSE
abundance-0.0.1b0.dist-info/METADATA
abundance-0.0.1b0.dist-info/WHEEL
abundance-0.0.1b0.dist-info/RECORD
